.gitignore
.status
LICENSE
README.md
run.py
setup.py
./handlers/__init__.py
./handlers/general.py
./handlers/util/__init__.py
./handlers/util/logger.py
./handlers/util/transport.py
./src/__init__.py
./src/configure.py
./src/reloader.py
./src/server.py
config.default/config.ini
handlers/__init__.py
handlers/__init__.pyc
handlers/general.py
handlers/general.pyc
handlers/util/__init__.py
handlers/util/__init__.pyc
handlers/util/logger.py
handlers/util/logger.pyc
handlers/util/transport.py
handlers/util/transport.pyc
routing.default/actions.ini
routing.default/alias.ini
routing.default/redirects.ini
routing.default/rules.ini
src/__init__.py
src/__init__.pyc
src/configure.py
src/reloader.py
src/server.py
src/server.pyc
toran.egg-info/PKG-INFO
toran.egg-info/SOURCES.txt
toran.egg-info/dependency_links.txt
toran.egg-info/requires.txt
toran.egg-info/top_level.txt