Metadata-Version: 1.0
Name: toran
Version: 0.0.1
Summary: Toran API server package
Home-page: https://github.com/rvegas/python-toran.git
Author: rvegas
Author-email: info@ricardo.vegas
License: MIT
Keywords: server api rest uwsgi toran
Platform: UNKNOWN
